django_graphene_authentication/__init__.py
django_graphene_authentication/admin.py
django_graphene_authentication/apps.py
django_graphene_authentication/backend.py
django_graphene_authentication/conf.py
django_graphene_authentication/decorators.py
django_graphene_authentication/managers.py
django_graphene_authentication/middleware.py
django_graphene_authentication/models.py
django_graphene_authentication/path.py
django_graphene_authentication/queries_and_mutations.py
django_graphene_authentication/relay.py
django_graphene_authentication/shortcuts.py
django_graphene_authentication/signals.py
django_graphene_authentication/utils.py
django_graphene_authentication/version.py
django_graphene_authentication/migrations/__init__.py
django_graphene_authentication/refresh_token/__init__.py
django_graphene_authentication/refresh_token/mixins.py
django_graphene_authentication/refresh_token/mutations.py
django_graphene_authentication/refresh_token/admin/__init__.py
django_graphene_authentication/refresh_token/admin/filters.py
django_graphene_authentication/refresh_token/management/__init__.py
django_graphene_authentication/refresh_token/management/commands/__init__.py
django_graphene_authentication/refresh_token/management/commands/cleartokens.py
django_graphene_authentication/refresh_token/migrations/0001_initial.py
django_graphene_authentication/refresh_token/migrations/0002_auto_20190130_0900.py
django_graphene_authentication/refresh_token/migrations/__init__.py
django_graphene_authentication-1.0.87.dist-info/LICENSE.md
django_graphene_authentication-1.0.87.dist-info/METADATA
django_graphene_authentication-1.0.87.dist-info/WHEEL
django_graphene_authentication-1.0.87.dist-info/top_level.txt
django_graphene_authentication-1.0.87.dist-info/RECORD
